khan_dl/__init__.py
khan_dl/__main__.py
khan_dl/khan_dl.py
khan_dl-1.2.9.dist-info/LICENSE
khan_dl-1.2.9.dist-info/METADATA
khan_dl-1.2.9.dist-info/WHEEL
khan_dl-1.2.9.dist-info/entry_points.txt
khan_dl-1.2.9.dist-info/RECORD
