Metadata-Version: 2.1
Name: khan-dl
Version: 1.2.9
Summary: Download courses from khanacademy.org
Home-page: https://github.com/rand-net/khan-dl
License: MIT
Keywords: khan academy,khan academy downloader,video downloader
Author: rand-net
Requires-Python: >=3.10,<4.0
Classifier: License :: OSI Approved :: MIT License
Classifier: Programming Language :: Python :: 3
Classifier: Programming Language :: Python :: 3.10
Classifier: Programming Language :: Python :: 3.11
Classifier: Programming Language :: Python :: 3.12
Classifier: Programming Language :: Python :: 3.7
Requires-Dist: art (>=6.1,<7.0)
Requires-Dist: beautifulsoup4 (>=4.12.3,<5.0.0)
Requires-Dist: lxml (>=5.1.0,<6.0.0)
Requires-Dist: prompt-toolkit (>=3.0.43,<4.0.0)
Requires-Dist: requests (>=2.31.0,<3.0.0)
Requires-Dist: yt-dlp (>=2024.07.01,<2025.0.0)
Project-URL: Repository, https://github.com/rand-net/khan-dl
